xnote/__init__.py
xnote/__main__.py
xnote/core/__init__.py
xnote/core/__version__.py
xnote/core/constants.py
xnote/core/cli/__init__.py
xnote/core/cli/xnote.py
xnote/core/codebase/__init__.py
xnote/core/codebase/note.py
xnote-1.1.dist-info/LICENSE
xnote-1.1.dist-info/METADATA
xnote-1.1.dist-info/WHEEL
xnote-1.1.dist-info/entry_points.txt
xnote-1.1.dist-info/top_level.txt
xnote-1.1.dist-info/RECORD
